<?xml version="1.0" encoding="UTF-8"?>
<MetaDataObject xmlns="http://v8.1c.ru/8.3/MDClasses" xmlns:app="http://v8.1c.ru/8.2/managed-application/core" xmlns:cfg="http://v8.1c.ru/8.1/data/enterprise/current-config" xmlns:cmi="http://v8.1c.ru/8.2/managed-application/cmi" xmlns:ent="http://v8.1c.ru/8.1/data/enterprise" xmlns:lf="http://v8.1c.ru/8.2/managed-application/logform" xmlns:style="http://v8.1c.ru/8.1/data/ui/style" xmlns:sys="http://v8.1c.ru/8.1/data/ui/fonts/system" xmlns:v8="http://v8.1c.ru/8.1/data/core" xmlns:v8ui="http://v8.1c.ru/8.1/data/ui" xmlns:web="http://v8.1c.ru/8.1/data/ui/colors/web" xmlns:win="http://v8.1c.ru/8.1/data/ui/colors/windows" xmlns:xen="http://v8.1c.ru/8.3/xcf/enums" xmlns:xpr="http://v8.1c.ru/8.3/xcf/predef" xmlns:xr="http://v8.1c.ru/8.3/xcf/readable" xmlns:xs="http://www.w3.org/2001/XMLSchema" xmlns:xsi="http://www.w3.org/2001/XMLSchema-instance" version="2.20">
	<DocumentJournal uuid="e1b7dc3b-2128-4628-a3d4-cdbf6ab30040">
		<InternalInfo>
			<xr:GeneratedType name="DocumentJournalSelection.бит_ОтраженияФактаДДС" category="Selection">
				<xr:TypeId>f58d7df9-b39b-4c37-99f8-d8fb23d61a5d</xr:TypeId>
				<xr:ValueId>c3142c61-1972-401a-badc-261a61ed6ec9</xr:ValueId>
			</xr:GeneratedType>
			<xr:GeneratedType name="DocumentJournalList.бит_ОтраженияФактаДДС" category="List">
				<xr:TypeId>eeb7586f-47f6-4fe0-9509-4a66e69cf9e3</xr:TypeId>
				<xr:ValueId>50a39fea-5bf1-4985-997f-5210605f0ae5</xr:ValueId>
			</xr:GeneratedType>
			<xr:GeneratedType name="DocumentJournalManager.бит_ОтраженияФактаДДС" category="Manager">
				<xr:TypeId>1d22cc9a-6dbe-43c7-9879-1c37c6927913</xr:TypeId>
				<xr:ValueId>cd5175c3-1f27-400a-a306-fe75f45e8c04</xr:ValueId>
			</xr:GeneratedType>
		</InternalInfo>
		<Properties>
			<Name>бит_ОтраженияФактаДДС</Name>
			<Synonym>
				<v8:item>
					<v8:lang>ru</v8:lang>
					<v8:content>Отражения факта ДДС</v8:content>
				</v8:item>
				<v8:item>
					<v8:lang>en</v8:lang>
					<v8:content>It reflects the fact DDS</v8:content>
				</v8:item>
			</Synonym>
			<Comment/>
			<DefaultForm>DocumentJournal.бит_ОтраженияФактаДДС.Form.ФормаСписка</DefaultForm>
			<AuxiliaryForm/>
			<UseStandardCommands>true</UseStandardCommands>
			<RegisteredDocuments>
				<xr:Item xsi:type="xr:MDObjectRef">Document.РасходныйКассовыйОрдер</xr:Item>
				<xr:Item xsi:type="xr:MDObjectRef">Document.ПриходныйКассовыйОрдер</xr:Item>
				<xr:Item xsi:type="xr:MDObjectRef">Document.ПоступлениеБезналичныхДенежныхСредств</xr:Item>
				<xr:Item xsi:type="xr:MDObjectRef">Document.СписаниеБезналичныхДенежныхСредств</xr:Item>
				<xr:Item xsi:type="xr:MDObjectRef">Document.ОтчетБанкаПоОперациямЭквайринга</xr:Item>
			</RegisteredDocuments>
			<IncludeHelpInContents>false</IncludeHelpInContents>
			<StandardAttributes>
				<xr:StandardAttribute name="Type">
					<xr:LinkByType/>
					<xr:FillChecking>DontCheck</xr:FillChecking>
					<xr:MultiLine>false</xr:MultiLine>
					<xr:FillFromFillingValue>false</xr:FillFromFillingValue>
					<xr:CreateOnInput>Auto</xr:CreateOnInput>
					<xr:TypeReductionMode>TransformValues</xr:TypeReductionMode>
					<xr:MaxValue xsi:nil="true"/>
					<xr:ToolTip/>
					<xr:ExtendedEdit>false</xr:ExtendedEdit>
					<xr:Format/>
					<xr:ChoiceForm/>
					<xr:QuickChoice>Auto</xr:QuickChoice>
					<xr:ChoiceHistoryOnInput>Auto</xr:ChoiceHistoryOnInput>
					<xr:EditFormat/>
					<xr:PasswordMode>false</xr:PasswordMode>
					<xr:DataHistory>Use</xr:DataHistory>
					<xr:MarkNegatives>false</xr:MarkNegatives>
					<xr:MinValue xsi:nil="true"/>
					<xr:Synonym/>
					<xr:Comment/>
					<xr:FullTextSearch>Use</xr:FullTextSearch>
					<xr:ChoiceParameterLinks/>
					<xr:FillValue xsi:nil="true"/>
					<xr:Mask/>
					<xr:ChoiceParameters/>
				</xr:StandardAttribute>
				<xr:StandardAttribute name="Ref">
					<xr:LinkByType/>
					<xr:FillChecking>DontCheck</xr:FillChecking>
					<xr:MultiLine>false</xr:MultiLine>
					<xr:FillFromFillingValue>false</xr:FillFromFillingValue>
					<xr:CreateOnInput>Auto</xr:CreateOnInput>
					<xr:TypeReductionMode>TransformValues</xr:TypeReductionMode>
					<xr:MaxValue xsi:nil="true"/>
					<xr:ToolTip/>
					<xr:ExtendedEdit>false</xr:ExtendedEdit>
					<xr:Format/>
					<xr:ChoiceForm/>
					<xr:QuickChoice>Auto</xr:QuickChoice>
					<xr:ChoiceHistoryOnInput>Auto</xr:ChoiceHistoryOnInput>
					<xr:EditFormat/>
					<xr:PasswordMode>false</xr:PasswordMode>
					<xr:DataHistory>Use</xr:DataHistory>
					<xr:MarkNegatives>false</xr:MarkNegatives>
					<xr:MinValue xsi:nil="true"/>
					<xr:Synonym/>
					<xr:Comment/>
					<xr:FullTextSearch>Use</xr:FullTextSearch>
					<xr:ChoiceParameterLinks/>
					<xr:FillValue xsi:nil="true"/>
					<xr:Mask/>
					<xr:ChoiceParameters/>
				</xr:StandardAttribute>
				<xr:StandardAttribute name="Date">
					<xr:LinkByType/>
					<xr:FillChecking>DontCheck</xr:FillChecking>
					<xr:MultiLine>false</xr:MultiLine>
					<xr:FillFromFillingValue>false</xr:FillFromFillingValue>
					<xr:CreateOnInput>Auto</xr:CreateOnInput>
					<xr:TypeReductionMode>TransformValues</xr:TypeReductionMode>
					<xr:MaxValue xsi:nil="true"/>
					<xr:ToolTip/>
					<xr:ExtendedEdit>false</xr:ExtendedEdit>
					<xr:Format/>
					<xr:ChoiceForm/>
					<xr:QuickChoice>Auto</xr:QuickChoice>
					<xr:ChoiceHistoryOnInput>Auto</xr:ChoiceHistoryOnInput>
					<xr:EditFormat/>
					<xr:PasswordMode>false</xr:PasswordMode>
					<xr:DataHistory>Use</xr:DataHistory>
					<xr:MarkNegatives>false</xr:MarkNegatives>
					<xr:MinValue xsi:nil="true"/>
					<xr:Synonym/>
					<xr:Comment/>
					<xr:FullTextSearch>Use</xr:FullTextSearch>
					<xr:ChoiceParameterLinks/>
					<xr:FillValue xsi:nil="true"/>
					<xr:Mask/>
					<xr:ChoiceParameters/>
				</xr:StandardAttribute>
				<xr:StandardAttribute name="Posted">
					<xr:LinkByType/>
					<xr:FillChecking>DontCheck</xr:FillChecking>
					<xr:MultiLine>false</xr:MultiLine>
					<xr:FillFromFillingValue>false</xr:FillFromFillingValue>
					<xr:CreateOnInput>Auto</xr:CreateOnInput>
					<xr:TypeReductionMode>TransformValues</xr:TypeReductionMode>
					<xr:MaxValue xsi:nil="true"/>
					<xr:ToolTip/>
					<xr:ExtendedEdit>false</xr:ExtendedEdit>
					<xr:Format/>
					<xr:ChoiceForm/>
					<xr:QuickChoice>Auto</xr:QuickChoice>
					<xr:ChoiceHistoryOnInput>Auto</xr:ChoiceHistoryOnInput>
					<xr:EditFormat/>
					<xr:PasswordMode>false</xr:PasswordMode>
					<xr:DataHistory>Use</xr:DataHistory>
					<xr:MarkNegatives>false</xr:MarkNegatives>
					<xr:MinValue xsi:nil="true"/>
					<xr:Synonym/>
					<xr:Comment/>
					<xr:FullTextSearch>Use</xr:FullTextSearch>
					<xr:ChoiceParameterLinks/>
					<xr:FillValue xsi:nil="true"/>
					<xr:Mask/>
					<xr:ChoiceParameters/>
				</xr:StandardAttribute>
				<xr:StandardAttribute name="DeletionMark">
					<xr:LinkByType/>
					<xr:FillChecking>DontCheck</xr:FillChecking>
					<xr:MultiLine>false</xr:MultiLine>
					<xr:FillFromFillingValue>false</xr:FillFromFillingValue>
					<xr:CreateOnInput>Auto</xr:CreateOnInput>
					<xr:TypeReductionMode>TransformValues</xr:TypeReductionMode>
					<xr:MaxValue xsi:nil="true"/>
					<xr:ToolTip/>
					<xr:ExtendedEdit>false</xr:ExtendedEdit>
					<xr:Format/>
					<xr:ChoiceForm/>
					<xr:QuickChoice>Auto</xr:QuickChoice>
					<xr:ChoiceHistoryOnInput>Auto</xr:ChoiceHistoryOnInput>
					<xr:EditFormat/>
					<xr:PasswordMode>false</xr:PasswordMode>
					<xr:DataHistory>Use</xr:DataHistory>
					<xr:MarkNegatives>false</xr:MarkNegatives>
					<xr:MinValue xsi:nil="true"/>
					<xr:Synonym/>
					<xr:Comment/>
					<xr:FullTextSearch>Use</xr:FullTextSearch>
					<xr:ChoiceParameterLinks/>
					<xr:FillValue xsi:nil="true"/>
					<xr:Mask/>
					<xr:ChoiceParameters/>
				</xr:StandardAttribute>
				<xr:StandardAttribute name="Number">
					<xr:LinkByType/>
					<xr:FillChecking>DontCheck</xr:FillChecking>
					<xr:MultiLine>false</xr:MultiLine>
					<xr:FillFromFillingValue>false</xr:FillFromFillingValue>
					<xr:CreateOnInput>Auto</xr:CreateOnInput>
					<xr:TypeReductionMode>TransformValues</xr:TypeReductionMode>
					<xr:MaxValue xsi:nil="true"/>
					<xr:ToolTip/>
					<xr:ExtendedEdit>false</xr:ExtendedEdit>
					<xr:Format/>
					<xr:ChoiceForm/>
					<xr:QuickChoice>Auto</xr:QuickChoice>
					<xr:ChoiceHistoryOnInput>Auto</xr:ChoiceHistoryOnInput>
					<xr:EditFormat/>
					<xr:PasswordMode>false</xr:PasswordMode>
					<xr:DataHistory>Use</xr:DataHistory>
					<xr:MarkNegatives>false</xr:MarkNegatives>
					<xr:MinValue xsi:nil="true"/>
					<xr:Synonym/>
					<xr:Comment/>
					<xr:FullTextSearch>Use</xr:FullTextSearch>
					<xr:ChoiceParameterLinks/>
					<xr:FillValue xsi:nil="true"/>
					<xr:Mask/>
					<xr:ChoiceParameters/>
				</xr:StandardAttribute>
			</StandardAttributes>
			<ListPresentation/>
			<ExtendedListPresentation>
				<v8:item>
					<v8:lang>ru</v8:lang>
					<v8:content>Отражения факта движения денежных средств</v8:content>
				</v8:item>
				<v8:item>
					<v8:lang>en</v8:lang>
					<v8:content>Reflect that cash flow</v8:content>
				</v8:item>
			</ExtendedListPresentation>
			<Explanation/>
		</Properties>
		<ChildObjects>
			<Column uuid="70737b64-9a2e-4d2d-a91e-fb15b09a16b2">
				<Properties>
					<Name>Организация</Name>
					<Synonym>
						<v8:item>
							<v8:lang>ru</v8:lang>
							<v8:content>Организация</v8:content>
						</v8:item>
						<v8:item>
							<v8:lang>en</v8:lang>
							<v8:content>Organization</v8:content>
						</v8:item>
					</Synonym>
					<Comment/>
					<Indexing>DontIndex</Indexing>
					<References>
						<xr:Item xsi:type="xr:MDObjectRef">Document.ПоступлениеБезналичныхДенежныхСредств.Attribute.Организация</xr:Item>
						<xr:Item xsi:type="xr:MDObjectRef">Document.ПриходныйКассовыйОрдер.Attribute.Организация</xr:Item>
						<xr:Item xsi:type="xr:MDObjectRef">Document.РасходныйКассовыйОрдер.Attribute.Организация</xr:Item>
						<xr:Item xsi:type="xr:MDObjectRef">Document.СписаниеБезналичныхДенежныхСредств.Attribute.Организация</xr:Item>
						<xr:Item xsi:type="xr:MDObjectRef">Document.ОтчетБанкаПоОперациямЭквайринга.Attribute.Организация</xr:Item>
					</References>
				</Properties>
			</Column>
			<Column uuid="1f79828b-df8d-4bc2-ad04-9e15a4444b59">
				<Properties>
					<Name>Контрагент</Name>
					<Synonym>
						<v8:item>
							<v8:lang>ru</v8:lang>
							<v8:content>Контрагент</v8:content>
						</v8:item>
						<v8:item>
							<v8:lang>en</v8:lang>
							<v8:content>Partner</v8:content>
						</v8:item>
					</Synonym>
					<Comment/>
					<Indexing>DontIndex</Indexing>
					<References>
						<xr:Item xsi:type="xr:MDObjectRef">Document.ПриходныйКассовыйОрдер.Attribute.Контрагент</xr:Item>
						<xr:Item xsi:type="xr:MDObjectRef">Document.РасходныйКассовыйОрдер.Attribute.Контрагент</xr:Item>
						<xr:Item xsi:type="xr:MDObjectRef">Document.СписаниеБезналичныхДенежныхСредств.Attribute.Контрагент</xr:Item>
						<xr:Item xsi:type="xr:MDObjectRef">Document.ПоступлениеБезналичныхДенежныхСредств.Attribute.Контрагент</xr:Item>
					</References>
				</Properties>
			</Column>
			<Column uuid="093ae446-7e31-436e-838e-658e7f4aa801">
				<Properties>
					<Name>Сумма</Name>
					<Synonym>
						<v8:item>
							<v8:lang>ru</v8:lang>
							<v8:content>Сумма</v8:content>
						</v8:item>
						<v8:item>
							<v8:lang>en</v8:lang>
							<v8:content>Amount</v8:content>
						</v8:item>
					</Synonym>
					<Comment/>
					<Indexing>DontIndex</Indexing>
					<References>
						<xr:Item xsi:type="xr:MDObjectRef">Document.ПоступлениеБезналичныхДенежныхСредств.Attribute.СуммаДокумента</xr:Item>
						<xr:Item xsi:type="xr:MDObjectRef">Document.ПриходныйКассовыйОрдер.Attribute.СуммаДокумента</xr:Item>
						<xr:Item xsi:type="xr:MDObjectRef">Document.РасходныйКассовыйОрдер.Attribute.СуммаДокумента</xr:Item>
						<xr:Item xsi:type="xr:MDObjectRef">Document.СписаниеБезналичныхДенежныхСредств.Attribute.СуммаДокумента</xr:Item>
						<xr:Item xsi:type="xr:MDObjectRef">Document.ОтчетБанкаПоОперациямЭквайринга.Attribute.СуммаДокумента</xr:Item>
					</References>
				</Properties>
			</Column>
			<Column uuid="412c3e9e-f2ba-47b9-a38d-27d1467b76b6">
				<Properties>
					<Name>Валюта</Name>
					<Synonym>
						<v8:item>
							<v8:lang>ru</v8:lang>
							<v8:content>Валюта</v8:content>
						</v8:item>
						<v8:item>
							<v8:lang>en</v8:lang>
							<v8:content>Currency</v8:content>
						</v8:item>
					</Synonym>
					<Comment/>
					<Indexing>DontIndex</Indexing>
					<References>
						<xr:Item xsi:type="xr:MDObjectRef">Document.ПоступлениеБезналичныхДенежныхСредств.Attribute.Валюта</xr:Item>
						<xr:Item xsi:type="xr:MDObjectRef">Document.ПриходныйКассовыйОрдер.Attribute.Валюта</xr:Item>
						<xr:Item xsi:type="xr:MDObjectRef">Document.РасходныйКассовыйОрдер.Attribute.Валюта</xr:Item>
						<xr:Item xsi:type="xr:MDObjectRef">Document.СписаниеБезналичныхДенежныхСредств.Attribute.Валюта</xr:Item>
						<xr:Item xsi:type="xr:MDObjectRef">Document.ОтчетБанкаПоОперациямЭквайринга.Attribute.Валюта</xr:Item>
					</References>
				</Properties>
			</Column>
			<Column uuid="4920af90-4b63-4cd6-958f-610783107b45">
				<Properties>
					<Name>ХозяйственнаяОперация</Name>
					<Synonym>
						<v8:item>
							<v8:lang>ru</v8:lang>
							<v8:content>Хозяйственная операция</v8:content>
						</v8:item>
						<v8:item>
							<v8:lang>en</v8:lang>
							<v8:content>business operation</v8:content>
						</v8:item>
					</Synonym>
					<Comment/>
					<Indexing>DontIndex</Indexing>
					<References>
						<xr:Item xsi:type="xr:MDObjectRef">Document.ПоступлениеБезналичныхДенежныхСредств.Attribute.ХозяйственнаяОперация</xr:Item>
						<xr:Item xsi:type="xr:MDObjectRef">Document.ПриходныйКассовыйОрдер.Attribute.ХозяйственнаяОперация</xr:Item>
						<xr:Item xsi:type="xr:MDObjectRef">Document.РасходныйКассовыйОрдер.Attribute.ХозяйственнаяОперация</xr:Item>
						<xr:Item xsi:type="xr:MDObjectRef">Document.СписаниеБезналичныхДенежныхСредств.Attribute.ХозяйственнаяОперация</xr:Item>
					</References>
				</Properties>
			</Column>
			<Form>ФормаСписка</Form>
		</ChildObjects>
	</DocumentJournal>
</MetaDataObject>